exceptioncontext.py
exceptioncontext-1.0.9.dist-info/LICENSE
exceptioncontext-1.0.9.dist-info/METADATA
exceptioncontext-1.0.9.dist-info/WHEEL
exceptioncontext-1.0.9.dist-info/top_level.txt
exceptioncontext-1.0.9.dist-info/RECORD
