Metadata-Version: 2.1
Name: exceptioncontext
Version: 1.0.9
Summary: Context managers for controlling exception chaining.
Home-page: https://github.com/mentalisttraceur/python-exceptioncontext
Author: Alexander Kozhevnikov
Author-email: mentalisttraceur@gmail.com
License: 0BSD
Platform: UNKNOWN
Classifier: Development Status :: 5 - Production/Stable
Classifier: Programming Language :: Python :: 3
Classifier: Programming Language :: Python :: 2
Classifier: Operating System :: OS Independent
License-File: LICENSE
